[{"id":1,"appointmentId":6,"patientId":10,"doctorId":3,"rating":5,"comment":"Great experience with the doctor. Very professional and knowledgeable.","createdAt":"2025-03-14 12:49:52.337"},{"id":2,"appointmentId":14,"patientId":10,"doctorId":5,"rating":5,"comment":"Great experience with the doctor. Very professional and knowledgeable.","createdAt":"2025-03-14 12:49:52.337"},{"id":3,"appointmentId":10,"patientId":9,"doctorId":5,"rating":4,"comment":"Great experience with the doctor. Very professional and knowledgeable.","createdAt":"2025-03-14 12:49:52.337"},{"id":4,"appointmentId":2,"patientId":10,"doctorId":6,"rating":5,"comment":"Great experience with the doctor. Very professional and knowledgeable.","createdAt":"2025-03-14 12:49:52.337"},{"id":5,"appointmentId":17,"patientId":9,"doctorId":6,"rating":4,"comment":"Great experience with the doctor. Very professional and knowledgeable.","createdAt":"2025-03-14 12:49:52.337"},{"id":6,"appointmentId":1,"patientId":9,"doctorId":3,"rating":5,"comment":"Great experience with the doctor. Very professional and knowledgeable.","createdAt":"2025-03-14 12:49:52.337"},{"id":7,"appointmentId":3,"patientId":10,"doctorId":4,"rating":4,"comment":"Great experience with the doctor. Very professional and knowledgeable.","createdAt":"2025-03-14 12:49:52.337"},{"id":8,"appointmentId":9,"patientId":9,"doctorId":4,"rating":5,"comment":"Great experience with the doctor. Very professional and knowledgeable.","createdAt":"2025-03-14 12:49:52.337"},{"id":9,"appointmentId":18,"patientId":10,"doctorId":7,"rating":5,"comment":"Great experience with the doctor. Very professional and knowledgeable.","createdAt":"2025-03-14 12:49:52.337"},{"id":10,"appointmentId":16,"patientId":9,"doctorId":7,"rating":4,"comment":"Great experience with the doctor. Very professional and knowledgeable.","createdAt":"2025-03-14 12:49:52.337"}]